{
  "zh-CN": {
    "version": "1.3.0",
    "description": "跨平台桌面座位安排与轮换系统，支持多种布局、策略引擎、插件扩展（开发中）和数据导入导出。",
    "projectUrl": "https://github.com/Helio-RC/Seatflow",
    "license": "MIT License",
    "copyright": "© 2026 SeatFlow Contributors",
    "dependencies": [
      { "name": "Avalonia UI", "packageId": "Avalonia", "purpose": "跨平台 UI 框架", "license": "MIT", "url": "https://github.com/AvaloniaUI/Avalonia" },
      { "name": "CommunityToolkit.Mvvm", "purpose": "MVVM 源生成器", "license": "MIT", "url": "https://github.com/CommunityToolkit/dotnet" },
      { "name": "FluentIcons.Avalonia", "purpose": "Fluent UI 系统图标", "license": "MIT", "url": "https://github.com/Seifzeid/FluentIcons.Avalonia" },
      { "name": "EPPlus", "purpose": "Excel 读写", "license": "PolyForm Noncommercial", "url": "https://github.com/EPPlusSoftware/EPPlus" },
      { "name": "CsvHelper", "purpose": "CSV 读写", "license": "Apache 2.0 / MS-PL", "url": "https://github.com/JoshClose/CsvHelper" },
      { "name": "QuestPDF", "purpose": "PDF 生成", "license": "MIT (Community)", "url": "https://github.com/QuestPDF/QuestPDF" },
      { "name": "NLua", "purpose": "Lua 脚本引擎", "license": "MIT", "url": "https://github.com/NLua/NLua" },
      { "name": "Serilog", "purpose": "结构化日志", "license": "Apache 2.0", "url": "https://github.com/serilog/serilog" }
    ]
  },
  "en-US": {
    "version": "1.3.0",
    "description": "Cross-platform desktop seating arrangement and rotation system supporting multiple layouts, strategy engines, plugin extensions (in development), and data import/export.",
    "projectUrl": "https://github.com/Helio-RC/Seatflow",
    "license": "MIT License",
    "copyright": "© 2026 SeatFlow Contributors",
    "dependencies": [
      { "name": "Avalonia UI", "packageId": "Avalonia", "purpose": "Cross-platform UI framework", "license": "MIT", "url": "https://github.com/AvaloniaUI/Avalonia" },
      { "name": "CommunityToolkit.Mvvm", "purpose": "MVVM source generator", "license": "MIT", "url": "https://github.com/CommunityToolkit/dotnet" },
      { "name": "FluentIcons.Avalonia", "purpose": "Fluent UI system icons", "license": "MIT", "url": "https://github.com/Seifzeid/FluentIcons.Avalonia" },
      { "name": "EPPlus", "purpose": "Excel read/write", "license": "PolyForm Noncommercial", "url": "https://github.com/EPPlusSoftware/EPPlus" },
      { "name": "CsvHelper", "purpose": "CSV read/write", "license": "Apache 2.0 / MS-PL", "url": "https://github.com/JoshClose/CsvHelper" },
      { "name": "QuestPDF", "purpose": "PDF generation", "license": "MIT (Community)", "url": "https://github.com/QuestPDF/QuestPDF" },
      { "name": "NLua", "purpose": "Lua scripting engine", "license": "MIT", "url": "https://github.com/NLua/NLua" },
      { "name": "Serilog", "purpose": "Structured logging", "license": "Apache 2.0", "url": "https://github.com/serilog/serilog" }
    ]
  }
}
